MANIFEST.in
README.md
setup.py
ajaximage/__init__.py
ajaximage/fields.py
ajaximage/forms.py
ajaximage/image.py
ajaximage/urls.py
ajaximage/views.py
ajaximage/widgets.py
ajaximage/static/ajaximage/css/bootstrap-progress.min.css
ajaximage/static/ajaximage/css/styles.css
ajaximage/static/ajaximage/js/ajaximage.js
django_ajaximage.egg-info/PKG-INFO
django_ajaximage.egg-info/SOURCES.txt
django_ajaximage.egg-info/dependency_links.txt
django_ajaximage.egg-info/not-zip-safe
django_ajaximage.egg-info/requires.txt
django_ajaximage.egg-info/top_level.txt